{
  "id" : "9a68de66-3c1a-4238-99ae-c8b19875b006",
  "name" : "Dastin Sandura",
  "bio" : "Inżynier oprogramowania działający w branży IT od 2015 roku. Obenie pracuje w roli Doświadczonego Konsultanta w GFT Poland. Przez 5 lat pracował w startupie w rolach, między innymi: front-end i back-end developera, konsultanta, dowódcy zespołu konsultantów, dowódcy działu wsparcia klienta oraz międzynarodowego trenera prowadzącego w języku angielskim szkolenia między innymi dla klientów takich jak SONY Interactive Entertainment i Tom Tom między innymi w biurach San Mateo - California, Las Vegas - Nevada, Monachium, Estonii oraz U.K. Współorganizator spotkań Domain Driven Design Gdańsk.",
  "twitter" : "https://twitter.com/dastin_it",
  "github" : "https://github.com/dastin-sandura",
  "www" : "https://dastin-sandura-software-developer.blogspot.com",
  "photo" : "/api/resources//photos/9a68de66-3c1a-4238-99ae-c8b19875b006.jpg"
}